genomicspy/Variants.py
genomicspy/__init__.py
genomicspy/alleles2fasta.py
genomicspy/cli.py
genomicspy/fasta.py
genomicspy/gff3.py
genomicspy/main.py
genomicspy/oed.py
genomicspy/records_chunk.py
genomicspy/records_saver.py
genomicspy/trim.py
genomicspy/vcf.py
genomicspy/alleles/Alleles.py
genomicspy/alleles/__init__.py
genomicspy/alleles/allele_msa.py
genomicspy/alleles/tools.py
genomicspy-0.2.1.dist-info/AUTHORS.rst
genomicspy-0.2.1.dist-info/LICENSE
genomicspy-0.2.1.dist-info/METADATA
genomicspy-0.2.1.dist-info/WHEEL
genomicspy-0.2.1.dist-info/entry_points.txt
genomicspy-0.2.1.dist-info/top_level.txt
genomicspy-0.2.1.dist-info/RECORD
