Metadata-Version: 2.1
Name: genomicspy
Version: 0.2.1
Summary: Tools for manipulating vcfs doing genomics work
Home-page: https://github.com/vivianleung/genomicspy
Author: Vivian Leung
Author-email: Vivian Leung <leung.vivian.w@gmail.com>
License: LGPL-2.1
Project-URL: Homepage, https://github.com/vivianleung/genomicspy
Project-URL: Bug Tracker, https://github.com/vivianleung/genomicspy/issues
Keywords: genomicspy,vcf,genomics
Classifier: Programming Language :: Python :: 3
Classifier: License :: OSI Approved :: MIT License
Classifier: Natural Language :: English
Classifier: Operating System :: OS Independent
Requires-Python: >=3.10
License-File: LICENSE
License-File: AUTHORS.rst
